README.md
setup.py
scikit_graph.egg-info/PKG-INFO
scikit_graph.egg-info/SOURCES.txt
scikit_graph.egg-info/dependency_links.txt
scikit_graph.egg-info/requires.txt
scikit_graph.egg-info/top_level.txt
skgraph/__init__.py