Metadata-Version: 1.0
Name: scikit-graph
Version: 0.1a0
Summary: A collection of tools and algorithms to augment those found in Scipy's csgraph module
Home-page: UNKNOWN
Author: PMEAL Team
Author-email: jgostick@uwaterloo.ca
License: UNKNOWN
Platform: UNKNOWN
